[
    {
        "model": "app.profile",
        "fields": {
            "familygroup": 1,
            "first_name": "Ned",
            "last_name": "Stark",
            "date_of_birth": "1950-10-25",
            "phone_number": "0671451467",
            "emergency_contact": "Catherine Tully",
            "docter_name_contact": "Dr. Luwin",
            "blood_type": "A RhD positive A+",
            "allergies": "Hay Fever",
            "existing_health_conditions": "None",
            "family_member_type": "Parent"
        }
    },
    {
        "model": "app.profile",
        "fields": {
            "familygroup": 1,
            "first_name": "Arya",
            "last_name": "Stark",
            "date_of_birth": "1978-03-17",
            "phone_number": "07834567813",
            "emergency_contact": "Catherine Tully",
            "docter_name_contact": "Dr. Luwin",
            "blood_type": "A RhD positive A+",
            "allergies": "None",
            "existing_health_conditions": "None",
            "family_member_type": "Child"
        }
    },
    {
        "model": "app.profile",
        "fields": {
            "familygroup": 2,
            "first_name": "Robert",
            "last_name": "Barratheon",
            "date_of_birth": "1950-04-15",
            "phone_number": "0687235677",
            "emergency_contact": "Ned Stark",
            "docter_name_contact": "Dr. Varys",
            "blood_type": "B RhD positive B+",
            "allergies": "Pollen",
            "existing_health_conditions": "Heart Disease",
            "family_member_type": "Parent"
        }
    },
    {
        "model": "app.profile",
        "fields": {
            "familygroup": 2,
            "first_name": "Jeoffrey",
            "last_name": "Barratheon",
            "date_of_birth": "1980-11-05",
            "phone_number": "0765425366",
            "emergency_contact": "Cersei Lannister",
            "docter_name_contact": "Dr. Varys",
            "blood_type": "B RhD positive B+",
            "allergies": "Grapes",
            "existing_health_conditions": "None",
            "family_member_type": "Child"
        }
    },
    {
        "model": "app.profile",
        "fields": {
            "familygroup": 3,
            "first_name": "Tywyn",
            "last_name": "Lannister",
            "date_of_birth": "1950-12-25",
            "phone_number": "0654489965",
            "emergency_contact": "Jaime Lannister",
            "docter_name_contact": "Dr. Qyburn",
            "blood_type": "O RhD positive O+",
            "allergies": "None",
            "existing_health_conditions": "None",
            "family_member_type": "Parent"
        }
    },
    {
        "model": "app.profile",
        "fields": {
            "familygroup": 3,
            "first_name": "Cersei",
            "last_name": "Lannister",
            "date_of_birth": "1975-07-10",
            "phone_number": "7923567356",
            "emergency_contact": "Jaime Lannister",
            "docter_name_contact": "Dr. Qyburn",
            "blood_type": "O RhD positive O+",
            "allergies": "Grapes",
            "existing_health_conditions": "None",
            "family_member_type": "Child"
        }
    },
    {
        "model": "app.profile",
        "fields": {
            "familygroup": 4,
            "first_name": "Daenerys",
            "last_name": "Targaryen",
            "date_of_birth": "1980-4-07",
            "phone_number": "3517687127",
            "emergency_contact": "John Snow",
            "docter_name_contact": "Dr. Viserys",
            "blood_type": "B RhD negative B-",
            "allergies": "None",
            "existing_health_conditions": "None",
            "family_member_type": "Parent"
        }
    },
    {
        "model": "app.profile",
        "fields": {
            "familygroup": 4,
            "first_name": "Drogon",
            "last_name": "Targaryen",
            "date_of_birth": "1990-05-24",
            "phone_number": "8768767564",
            "emergency_contact": "Khal Drogo",
            "docter_name_contact": "Dr. Viserys",
            "blood_type": "B RhD negative B-",
            "allergies": "None",
            "existing_health_conditions": "None",
            "family_member_type": "Child"
        }
    }
]